geniusrise_vision/__init__.py
geniusrise_vision/base/__init__.py
geniusrise_vision/base/api.py
geniusrise_vision/base/bulk.py
geniusrise_vision/base/communication.py
geniusrise_vision/base/fine_tune.py
geniusrise_vision/imgclass/__init__.py
geniusrise_vision/imgclass/api.py
geniusrise_vision/imgclass/bulk.py
geniusrise_vision/imgclass/fine_tune.py
geniusrise_vision/imgclass/tests/__init__.py
geniusrise_vision/imgclass/tests/test_api.py
geniusrise_vision/imgclass/tests/test_bulk.py
geniusrise_vision/imgclass/tests/test_fine_tune.py
geniusrise_vision/ocr/__init__.py
geniusrise_vision/ocr/api.py
geniusrise_vision/ocr/bulk.py
geniusrise_vision/ocr/fine_tune.py
geniusrise_vision/ocr/utils.py
geniusrise_vision/ocr/tests/__init__.py
geniusrise_vision/ocr/tests/test_api.py
geniusrise_vision/ocr/tests/test_bulk.py
geniusrise_vision/ocr/tests/test_fine_tune.py
geniusrise_vision/segment/__init__.py
geniusrise_vision/segment/api.py
geniusrise_vision/segment/bulk.py
geniusrise_vision/segment/fine_tune.py
geniusrise_vision/segment/tests/__init__.py
geniusrise_vision/segment/tests/test_api.py
geniusrise_vision/segment/tests/test_bulk.py
geniusrise_vision/segment/tests/test_fine_tune.py
geniusrise_vision/vqa/__init__.py
geniusrise_vision/vqa/api.py
geniusrise_vision-0.1.5.dist-info/LICENSE
geniusrise_vision-0.1.5.dist-info/METADATA
geniusrise_vision-0.1.5.dist-info/WHEEL
geniusrise_vision-0.1.5.dist-info/top_level.txt
geniusrise_vision-0.1.5.dist-info/RECORD
