Metadata-Version: 2.1
Name: geniusrise-vision
Version: 0.1.5
Summary: Huggingface bolts for geniusrise
Home-page: https://github.com/geniusrise/geniusrise-vision
Author: ixaxaar
Author-email: ixaxaar@geniusrise.ai
Project-URL: Bug Reports, https://github.com/geniusrise/geniusrise-vision/issues
Project-URL: Source, https://github.com/geniusrise/geniusrise-vision
Project-URL: Documentation, https://docs.geniusrise.ai/
Keywords: mlops,llm,geniusrise,machine learning,data processing
Classifier: Development Status :: 3 - Alpha
Classifier: Intended Audience :: Developers
Classifier: Topic :: Software Development :: Build Tools
Classifier: License :: OSI Approved :: Apache Software License
Classifier: Programming Language :: Python :: 3.10
Classifier: Programming Language :: Python :: 3.11
Classifier: Programming Language :: Python :: 3.12
Classifier: Operating System :: OS Independent
Requires-Python: >=3.10
License-File: LICENSE
Requires-Dist: geniusrise ==0.1.7
Requires-Dist: torch ==2.2.0
Requires-Dist: accelerate ==0.27.2
Requires-Dist: transformers ==4.36.2
Requires-Dist: evaluate ==0.4.1
Requires-Dist: datasets ==2.16.1
Requires-Dist: autoawq ==0.2.2
Requires-Dist: auto-gptq ==0.7.0
Requires-Dist: bitsandbytes ==0.42.0
Requires-Dist: CherryPy ==18.9.0
Requires-Dist: flash-attn ==2.5.3
Requires-Dist: peft ==0.7.1
Requires-Dist: gunicorn ==21.2.0
Requires-Dist: trl ==0.7.10
Requires-Dist: sentence-transformers ==2.2.2
Requires-Dist: nbformat ==5.9.2
Requires-Dist: sacremoses ==0.1.1
Requires-Dist: sacrebleu ==2.4.0
Requires-Dist: rouge-score ==0.1.2
Requires-Dist: rouge ==1.0.1
Requires-Dist: openpyxl ==3.1.2
Requires-Dist: sentencepiece ==0.1.99
Requires-Dist: safetensors ==0.4.1
Requires-Dist: einops ==0.7.0
Requires-Dist: optimum ==1.16.2
Requires-Dist: textwrap3 ==0.9.2
Requires-Dist: nltk ==3.8.1
Requires-Dist: pyarrow >=9.0.0
Requires-Dist: absl-py ==2.1.0
Requires-Dist: pandas ==1.3.5
Requires-Dist: torchvision ==0.17.0
Requires-Dist: torchaudio ==2.2.0
Requires-Dist: Pillow ==10.0.1
Requires-Dist: opencv-python ==4.6.0.66
Requires-Dist: pdf2image ==1.17.0
Requires-Dist: prompt-toolkit ==3.0.43
Requires-Dist: scikit-image ==0.22.0
Requires-Dist: easyocr ==1.7.1
Requires-Dist: paddleocr ==2.7.0.3
Requires-Dist: paddlepaddle ==2.6.0
Requires-Dist: pdf2docx ==0.5.8
Requires-Dist: PyMuPDF ==1.20.2
Requires-Dist: python-Levenshtein ==0.25.0
Requires-Dist: uform ==1.1.0
Requires-Dist: multiprocess ==0.70.15
Provides-Extra: dev
Requires-Dist: check-manifest ; extra == 'dev'
Provides-Extra: test
Requires-Dist: coverage ; extra == 'test'
